ribes/__init__.py
ribes/app.py
ribes/caller.py
ribes/dispatcher.py
ribes/errors.py
ribes/models.py
ribes/settings.py
ribes-0.1.2.dist-info/LICENSE
ribes-0.1.2.dist-info/METADATA
ribes-0.1.2.dist-info/WHEEL
ribes-0.1.2.dist-info/top_level.txt
ribes-0.1.2.dist-info/RECORD
